clandestino/__init__.py
clandestino/clandestino.py
clandestino/src/__init__.py
clandestino/src/ref.py
clandestino-0.1.14.dist-info/LICENSE
clandestino-0.1.14.dist-info/METADATA
clandestino-0.1.14.dist-info/WHEEL
clandestino-0.1.14.dist-info/entry_points.txt
clandestino-0.1.14.dist-info/RECORD
