Metadata-Version: 2.1
Name: clandestino
Version: 0.1.14
Summary: Simple migration tool for your python project
Author: XimitGaia
Author-email: im.ximit@gmail.com
Requires-Python: >=3.11,<4.0
Classifier: Programming Language :: Python :: 3
Classifier: Programming Language :: Python :: 3.11
Classifier: Programming Language :: Python :: 3.12
Provides-Extra: elasticsearch
Provides-Extra: minio
Provides-Extra: mongo
Provides-Extra: postgres
Provides-Extra: qdrant
Provides-Extra: sqlite
Requires-Dist: clandestino-interfaces (>=0.1.1,<0.2.0)
Requires-Dist: clandestino_elasticsearch (>=0.1.1,<0.2.0) ; extra == "elasticsearch"
Requires-Dist: clandestino_minio (>=0.1.1,<0.2.0) ; extra == "minio"
Requires-Dist: clandestino_mongo (>=0.1.1,<0.2.0) ; extra == "mongo"
Requires-Dist: clandestino_postgres (>=0.1.1,<0.2.0) ; extra == "postgres"
Requires-Dist: clandestino_qdrant (>=0.1.1,<0.2.0) ; extra == "qdrant"
Requires-Dist: clandestino_sqlite (>=0.1.3,<0.2.0) ; extra == "sqlite"
Requires-Dist: python-decouple (>=3.8,<4.0)
Project-URL: bugs, https://github.com/CenturyBoys/clandestino/issues
Project-URL: documentation, https://github.com/CenturyBoys/clandestino/blob/main/README.md
Project-URL: homepage, https://github.com/CenturyBoys/clandestino
Project-URL: repository, https://github.com/CenturyBoys/clandestino/tree/main
